polympiads_statelessauth-1.0.1.dist-info/licenses/LICENSE.md
statelessauth/__init__.py
statelessauth/config.py
statelessauth/middlewares.py
statelessauth/prometheus.py
statelessauth/wire.py
statelessauth/contrib/__init__.py
statelessauth/contrib/auth/__init__.py
statelessauth/contrib/auth/models.py
statelessauth/contrib/auth/views.py
statelessauth/contrib/auth/wire.py
statelessauth/engine/__init__.py
statelessauth/engine/abstract.py
statelessauth/engine/acquire.py
statelessauth/engine/refresh.py
polympiads_statelessauth-1.0.1.dist-info/METADATA
polympiads_statelessauth-1.0.1.dist-info/WHEEL
polympiads_statelessauth-1.0.1.dist-info/top_level.txt
polympiads_statelessauth-1.0.1.dist-info/RECORD
