Metadata-Version: 2.4
Name: polympiads_statelessauth
Version: 1.0.1
Summary: Polympiads Framework for Stateless Auth
Home-page: https://polympiads.github.io/statelessauth
Author: Polympiads
License: MIT
Project-URL: About Polympiads, https://polympiads.ch/
Project-URL: Source, https://github.com/polympiads/statelessauth
Classifier: Development Status :: 3 - Alpha
Classifier: Intended Audience :: Developers
Classifier: License :: OSI Approved :: MIT License
Classifier: Operating System :: OS Independent
License-File: LICENSE.md
Requires-Dist: django
Requires-Dist: coverage
Requires-Dist: python-jose
Requires-Dist: django-prometheus
Requires-Dist: prometheus-client
Dynamic: author
Dynamic: classifier
Dynamic: description
Dynamic: description-content-type
Dynamic: home-page
Dynamic: license
Dynamic: license-file
Dynamic: project-url
Dynamic: requires-dist
Dynamic: summary
